selenium-4.7.2.dist-info/METADATA
selenium-4.7.2.dist-info/RECORD
selenium-4.7.2.dist-info/WHEEL
selenium/__init__.py
selenium/common/__init__.py
selenium/common/exceptions.py
selenium/py.typed
selenium/types.py
selenium/webdriver/__init__.py
selenium/webdriver/chrome/__init__.py
selenium/webdriver/chrome/options.py
selenium/webdriver/chrome/service.py
selenium/webdriver/chrome/webdriver.py
selenium/webdriver/chromium/__init__.py
selenium/webdriver/chromium/options.py
selenium/webdriver/chromium/remote_connection.py
selenium/webdriver/chromium/service.py
selenium/webdriver/chromium/webdriver.py
selenium/webdriver/common/__init__.py
selenium/webdriver/common/action_chains.py
selenium/webdriver/common/actions/__init__.py
selenium/webdriver/common/actions/action_builder.py
selenium/webdriver/common/actions/input_device.py
selenium/webdriver/common/actions/interaction.py
selenium/webdriver/common/actions/key_actions.py
selenium/webdriver/common/actions/key_input.py
selenium/webdriver/common/actions/mouse_button.py
selenium/webdriver/common/actions/pointer_actions.py
selenium/webdriver/common/actions/pointer_input.py
selenium/webdriver/common/actions/wheel_actions.py
selenium/webdriver/common/actions/wheel_input.py
selenium/webdriver/common/alert.py
selenium/webdriver/common/bidi/__init__.py
selenium/webdriver/common/bidi/cdp.py
selenium/webdriver/common/bidi/console.py
selenium/webdriver/common/by.py
selenium/webdriver/common/desired_capabilities.py
selenium/webdriver/common/devtools/v106/__init__.py
selenium/webdriver/common/devtools/v106/accessibility.py
selenium/webdriver/common/devtools/v106/animation.py
selenium/webdriver/common/devtools/v106/audits.py
selenium/webdriver/common/devtools/v106/background_service.py
selenium/webdriver/common/devtools/v106/browser.py
selenium/webdriver/common/devtools/v106/cache_storage.py
selenium/webdriver/common/devtools/v106/cast.py
selenium/webdriver/common/devtools/v106/console.py
selenium/webdriver/common/devtools/v106/css.py
selenium/webdriver/common/devtools/v106/database.py
