Metadata-Version: 2.1
Name: selenium
Version: 4.7.2
Home-page: https://www.selenium.dev
License: Apache 2.0
Classifier: Development Status :: 5 - Production/Stable
Classifier: Intended Audience :: Developers
Classifier: License :: OSI Approved :: Apache Software License
Classifier: Operating System :: POSIX
Classifier: Operating System :: Microsoft :: Windows
Classifier: Operating System :: MacOS :: MacOS X
Classifier: Topic :: Software Development :: Testing
Classifier: Topic :: Software Development :: Libraries
Classifier: Programming Language :: Python
Classifier: Programming Language :: Python :: 3.7
Classifier: Programming Language :: Python :: 3.8
Classifier: Programming Language :: Python :: 3.9
Classifier: Programming Language :: Python :: 3.10
Requires-Python: ~=3.7
Requires-Dist: urllib3[socks]~=1.26
Requires-Dist: trio~=0.17
Requires-Dist: trio-websocket~=0.9
Requires-Dist: certifi>=2021.10.8
